pythy/__init__.py
pythy/backend.py
pythy/regex.py
pythy/sockapi.py
pythy/split.py
pythy/variable.py
pythy/wrappers.py
pythy/sockapi-server/Makefile
pythy/sockapi-server/dispatcher.h
pythy/sockapi-server/dispatcher.s
pythy/sockapi-server/make.sh
pythy/sockapi-server/sockapi.c
pythy/sockapi-server/socklib.c
pythy/sockapi-server/socklib.h
pythy/sockapi-server/vg-log.txt
pythy-0.0.1.dist-info/LICENSE
pythy-0.0.1.dist-info/METADATA
pythy-0.0.1.dist-info/WHEEL
pythy-0.0.1.dist-info/top_level.txt
pythy-0.0.1.dist-info/RECORD
