Metadata-Version: 2.1
Name: pythy
Version: 0.0.1
Summary: Clean interface into compiled code
Author-email: Alex Craig <example@example.com>
Classifier: Programming Language :: Python :: 3
Classifier: License :: OSI Approved :: MIT License
Classifier: Operating System :: POSIX :: Linux
Requires-Python: >=3.7
License-File: LICENSE
